odoo/addons/shopinvader_product_brand_tag/README.rst
odoo/addons/shopinvader_product_brand_tag/__init__.py
odoo/addons/shopinvader_product_brand_tag/__manifest__.py
odoo/addons/shopinvader_product_brand_tag/i18n/shopinvader_product_brand_tag.pot
odoo/addons/shopinvader_product_brand_tag/readme/CONTRIBUTORS.rst
odoo/addons/shopinvader_product_brand_tag/readme/DESCRIPTION.rst
odoo/addons/shopinvader_product_brand_tag/schemas/__init__.py
odoo/addons/shopinvader_product_brand_tag/schemas/brand.py
odoo/addons/shopinvader_product_brand_tag/schemas/brand_tag.py
odoo/addons/shopinvader_product_brand_tag/static/description/index.html
odoo_addon_shopinvader_product_brand_tag-16.0.1.0.1.dist-info/METADATA
odoo_addon_shopinvader_product_brand_tag-16.0.1.0.1.dist-info/WHEEL
odoo_addon_shopinvader_product_brand_tag-16.0.1.0.1.dist-info/top_level.txt
odoo_addon_shopinvader_product_brand_tag-16.0.1.0.1.dist-info/RECORD
