Metadata-Version: 2.1
Name: odoo-addon-shopinvader-product-brand-tag
Version: 16.0.1.0.1
Summary: Index Product Brand Tags in Shopinvader
Home-page: https://github.com/shopinvader/odoo-shopinvader
Author: Camptocamp,ACSONE SA/NV
License: AGPL-3
Platform: UNKNOWN
Classifier: Programming Language :: Python
Classifier: Framework :: Odoo
Classifier: Framework :: Odoo :: 16.0
Classifier: License :: OSI Approved :: GNU Affero General Public License v3
Classifier: Development Status :: 3 - Alpha
Requires-Python: >=3.10
Requires-Dist: extendable-pydantic >=1.2.0
Requires-Dist: odoo-addon-product-brand-tag <16.1dev,>=16.0dev
Requires-Dist: odoo-addon-shopinvader-product-brand <16.1dev,>=16.0dev
Requires-Dist: odoo <16.1dev,>=16.0a
